pyimzml/ImzMLParser.py
pyimzml/ImzMLWriter.py
pyimzml/__init__.py
pyimzml/compression.py
pyimzml/metadata.py
pyimzml/ontology/__init__.py
pyimzml/ontology/dump_obo_files.py
pyimzml/ontology/ims.py
pyimzml/ontology/ms.py
pyimzml/ontology/ontology.py
pyimzml/ontology/uo.py
pyimzML-1.5.5.dist-info/LICENSE
pyimzML-1.5.5.dist-info/METADATA
pyimzML-1.5.5.dist-info/WHEEL
pyimzML-1.5.5.dist-info/top_level.txt
pyimzML-1.5.5.dist-info/RECORD
