Metadata-Version: 1.1
Name: pyimzML
Version: 1.5.5
Summary: Parser for conversion of imzML 1.1.0 files
Home-page: https://github.com/alexandrovteam/pyimzML
Author: Alexandrov Team, EMBL
Author-email: theodore.alexandrov@embl.de
License: Apache 2.0
Keywords: bioinformatics imaging mass spectrometry parser imzML
Platform: UNKNOWN
Classifier: Development Status :: 5 - Production/Stable
Classifier: Intended Audience :: Developers
Classifier: Intended Audience :: Science/Research
Classifier: Topic :: Scientific/Engineering :: Bio-Informatics
Classifier: License :: OSI Approved :: Apache Software License
Classifier: Programming Language :: Python :: 3
Classifier: Programming Language :: Python :: 3.8
